jirit/__init__.py
jirit/jirit.py
jirit/jirit_shell.py
jirit-1.3.5.dist-info/top_level.txt
jirit-1.3.5.dist-info/METADATA
jirit-1.3.5.dist-info/DESCRIPTION.rst
jirit-1.3.5.dist-info/WHEEL
jirit-1.3.5.dist-info/RECORD
jirit-1.3.5.dist-info/entry_points.txt
jirit-1.3.5.dist-info/metadata.json
