Metadata-Version: 2.0
Name: jirit
Version: 1.3.5
Summary: Jirit is for getting stuff from Jira and Github.
Home-page: https://github.com/onepercentclub/jirit-py
Author: 1%Club
Author-email: devteam@onepercentclub.com
License: BSD
Platform: any
Classifier: Development Status :: 4 - Beta
Classifier: Intended Audience :: Developers
Classifier: Operating System :: Unix
Classifier: Programming Language :: Python
Classifier: Programming Language :: Python :: 2.7
Classifier: Topic :: Software Development :: Libraries :: Python Modules
Provides: jirit
Requires-Dist: jira (==1.0.7)
Requires-Dist: PyGithub (==1.27.1)
Requires-Dist: PyCrypto (==2.6.1)
Provides-Extra: test
